splotch/__init__.py
splotch/dataclasses.py
splotch/inference.py
splotch/models.py
splotch/registration.py
splotch/utils.py
splotch/visualization.py
splotch_st-1.0.0.dist-info/LICENSE
splotch_st-1.0.0.dist-info/METADATA
splotch_st-1.0.0.dist-info/WHEEL
splotch_st-1.0.0.dist-info/entry_points.txt
splotch_st-1.0.0.dist-info/RECORD
