Metadata-Version: 2.1
Name: splotch-st
Version: 1.0.0
Summary: Splotch is a hierarchical generative probabilistic model for analyzing Spatial Transcriptomics (ST) data
Home-page: https://github.com/tare/Splotch
License: MIT
Author: Tarmo Äijö
Author-email: tarmo.aijo@gmail.com
Requires-Python: >=3.10,<4.0
Classifier: Development Status :: 4 - Beta
Classifier: Intended Audience :: Science/Research
Classifier: License :: OSI Approved :: MIT License
Classifier: Programming Language :: Python :: 3
Classifier: Programming Language :: Python :: 3.10
Classifier: Programming Language :: Python :: 3.11
Classifier: Programming Language :: Python :: 3.12
Classifier: Programming Language :: Python :: 3.13
Classifier: Topic :: Scientific/Engineering :: Bio-Informatics
Provides-Extra: examples
Requires-Dist: funsor (>=0.4,<0.5)
Requires-Dist: ipywidgets (>=8.1.1,<9.0.0) ; extra == "examples"
Requires-Dist: jax (<=0.4.30)
Requires-Dist: jaxlib (<=0.4.30)
Requires-Dist: jupyterlab (>=4.0.8,<5.0.0) ; extra == "examples"
Requires-Dist: matplotlib (>=3.8.1,<4.0.0)
Requires-Dist: networkx (>=3.2,<4.0)
Requires-Dist: numpyro (>=0.15,<0.16)
Requires-Dist: pandas (>=2,<3)
Requires-Dist: pillow (>=10.1,<11.0)
Requires-Dist: scipy (>=1.14,<2.0)
Project-URL: Bug Tracker, https://github.com/tare/Splotch/issues
Project-URL: Repository, https://github.com/tare/Splotch
